collective.privacy-1.0a1-py2.7-nspkg.pth
collective/privacy/__init__.py
collective/privacy/configure.zcml
collective/privacy/identifiers.py
collective/privacy/interfaces.py
collective/privacy/lawful_basis.py
collective/privacy/lawful_basis.zcml
collective/privacy/meta.zcml
collective/privacy/permissions.zcml
collective/privacy/processing_reason.py
collective/privacy/setuphandlers.py
collective/privacy/storage.py
collective/privacy/storage.zcml
collective/privacy/testing.py
collective/privacy/tool.py
collective/privacy/upgrades.py
collective/privacy/upgrades.zcml
collective/privacy/zcml.py
collective/privacy/browser/__init__.py
collective/privacy/browser/configure.zcml
collective/privacy/browser/consent.py
collective/privacy/browser/overrides/.gitkeep
collective/privacy/browser/overrides/Products.CMFPlone.browser.templates.sendto_template.pt
collective/privacy/browser/overrides/Products.CMFPlone.skins.plone_form_scripts.validate_sendto.vpy
collective/privacy/browser/overrides/Products.CMFPlone.skins.plone_templates.sendto_template.pt
collective/privacy/browser/static/.gitkeep
collective/privacy/browser/templates/consent_banner.pt
collective/privacy/locales/collective.privacy.pot
collective/privacy/locales/update.sh
collective/privacy/plone_core/__init__.py
collective/privacy/plone_core/configure.zcml
collective/privacy/plone_core/sendto.py
collective/privacy/plone_core/webstats_js.py
collective/privacy/profiles/default/browserlayer.xml
collective/privacy/profiles/default/catalog.xml
collective/privacy/profiles/default/componentregistry.xml
collective/privacy/profiles/default/metadata.xml
collective/privacy/profiles/default/registry.xml
collective/privacy/profiles/default/rolemap.xml
collective/privacy/profiles/default/toolset.xml
collective/privacy/profiles/uninstall/browserlayer.xml
collective/privacy/tests/__init__.py
collective/privacy/tests/test_robot.py
collective/privacy/tests/test_setup.py
collective.privacy-1.0a1.dist-info/DESCRIPTION.rst
collective.privacy-1.0a1.dist-info/METADATA
collective.privacy-1.0a1.dist-info/RECORD
collective.privacy-1.0a1.dist-info/WHEEL
collective.privacy-1.0a1.dist-info/entry_points.txt
collective.privacy-1.0a1.dist-info/metadata.json
collective.privacy-1.0a1.dist-info/namespace_packages.txt
collective.privacy-1.0a1.dist-info/top_level.txt
