Metadata-Version: 2.0
Name: collective.privacy
Version: 1.0a1
Summary: An add-on for Plone that provides functionality for better complying with the EU's General Data Protection Regulations and ePrivacy Regulations
Home-page: https://pypi.python.org/pypi/collective.privacy
Author: Matthew Wilkes
Author-email: matt@matthewwilkes.name
License: GPL version 2
Keywords: Python Plone
Platform: UNKNOWN
Classifier: Environment :: Web Environment
Classifier: Framework :: Plone
Classifier: Framework :: Plone :: 5.0
Classifier: Framework :: Plone :: 5.1
Classifier: Programming Language :: Python
Classifier: Programming Language :: Python :: 2.7
Classifier: Operating System :: OS Independent
Classifier: License :: OSI Approved :: GNU General Public License v2 (GPLv2)
Provides-Extra: test
Requires-Dist: plone.api (>=1.8.4)
Requires-Dist: Products.GenericSetup (>=1.8.2)
Requires-Dist: setuptools
Requires-Dist: z3c.jbot
Requires-Dist: plone.app.dexterity (<=2.1.1)
Requires-Dist: plone.app.referenceablebehavior
Requires-Dist: plone.app.relationfield
Requires-Dist: plone.app.lockingbehavior
Requires-Dist: plone.schema
Requires-Dist: plone.directives.form
Provides-Extra: test
Requires-Dist: plone.app.testing; extra == 'test'
Requires-Dist: plone.testing (>=5.0.0); extra == 'test'
Requires-Dist: plone.app.robotframework[debug]; extra == 'test'
